Tensorflow24GuanfangJiaochengHeZhinanFix1/README.md
Tensorflow24GuanfangJiaochengHeZhinanFix1/__init__.py
Tensorflow24GuanfangJiaochengHeZhinanFix1/__main__.py
Tensorflow24GuanfangJiaochengHeZhinanFix1/file.epub
Tensorflow24GuanfangJiaochengHeZhinanFix1/index.html
Tensorflow24GuanfangJiaochengHeZhinanFix1/css/__init__.py
Tensorflow24GuanfangJiaochengHeZhinanFix1/css/annotations.css
Tensorflow24GuanfangJiaochengHeZhinanFix1/css/main.css
Tensorflow24GuanfangJiaochengHeZhinanFix1/css/normalize.css
Tensorflow24GuanfangJiaochengHeZhinanFix1/css/popup.css
Tensorflow24GuanfangJiaochengHeZhinanFix1/font/__init__.py
Tensorflow24GuanfangJiaochengHeZhinanFix1/font/fontello.eot
Tensorflow24GuanfangJiaochengHeZhinanFix1/font/fontello.svg
Tensorflow24GuanfangJiaochengHeZhinanFix1/font/fontello.ttf
Tensorflow24GuanfangJiaochengHeZhinanFix1/font/fontello.woff
Tensorflow24GuanfangJiaochengHeZhinanFix1/img/__init__.py
Tensorflow24GuanfangJiaochengHeZhinanFix1/img/annotator-glyph-sprite.png
Tensorflow24GuanfangJiaochengHeZhinanFix1/img/annotator-icon-sprite.png
Tensorflow24GuanfangJiaochengHeZhinanFix1/img/apple-touch-icon.png
Tensorflow24GuanfangJiaochengHeZhinanFix1/img/cancelfullscreen.png
Tensorflow24GuanfangJiaochengHeZhinanFix1/img/close.png
Tensorflow24GuanfangJiaochengHeZhinanFix1/img/fullscreen.png
Tensorflow24GuanfangJiaochengHeZhinanFix1/img/loader.gif
Tensorflow24GuanfangJiaochengHeZhinanFix1/img/menu-icon.png
Tensorflow24GuanfangJiaochengHeZhinanFix1/img/save.png
Tensorflow24GuanfangJiaochengHeZhinanFix1/img/saved.png
Tensorflow24GuanfangJiaochengHeZhinanFix1/img/settings-s.png
Tensorflow24GuanfangJiaochengHeZhinanFix1/img/settings.png
Tensorflow24GuanfangJiaochengHeZhinanFix1/img/star.png
Tensorflow24GuanfangJiaochengHeZhinanFix1/js/__init__.py
Tensorflow24GuanfangJiaochengHeZhinanFix1/js/epub.js
Tensorflow24GuanfangJiaochengHeZhinanFix1/js/epub.min.js
Tensorflow24GuanfangJiaochengHeZhinanFix1/js/epub.min.map
Tensorflow24GuanfangJiaochengHeZhinanFix1/js/hooks.min.js
tensorflow_2_4_guanfang_jiaocheng_he_zhinan_fix1-2025.3.24.1.dist-info/METADATA
tensorflow_2_4_guanfang_jiaocheng_he_zhinan_fix1-2025.3.24.1.dist-info/WHEEL
tensorflow_2_4_guanfang_jiaocheng_he_zhinan_fix1-2025.3.24.1.dist-info/entry_points.txt
tensorflow_2_4_guanfang_jiaocheng_he_zhinan_fix1-2025.3.24.1.dist-info/top_level.txt
tensorflow_2_4_guanfang_jiaocheng_he_zhinan_fix1-2025.3.24.1.dist-info/RECORD
